{
  "schema_version": "v1",
  "name_for_human": "TickTick Gamification",
  "name_for_model": "ticktick_gamification",
  "description_for_human": "Gamify your TickTick tasks with XP, coins, and streaks.",
  "description_for_model": "Uses TickTick's API to fetch tasks and track recurring habits for gamification.",
  "auth": {
    "type": "oauth",
    "client_url": "https://ticktick-gamification.onrender.com/oauth/authorize",
    "authorization_url": "https://ticktick-gamification.onrender.com/oauth/authorize",
    "token_url": "https://ticktick-gamification.onrender.com/oauth/token",
    "redirect_uri": "https://ticktick-gamification.onrender.com/api/oauth/callback",
    "scope": "tasks:read"
  },
  "api": {
    "type": "openapi",
    "url": "https://ticktick-gamification.onrender.com/openapi.yaml",
    "is_user_authenticated": true
  },
  "logo_url": "https://ticktick-gamification.onrender.com/icon.png",
  "contact_email": "you@ticktickgamification.dev",
  "legal_info_url": "https://ticktick-gamification.onrender.com/legal"
}
